fuchur/__init__.py
fuchur/__main__.py
fuchur/cli.py
fuchur-0.0.0.dist-info/AUTHORS.rst
fuchur-0.0.0.dist-info/LICENSE
fuchur-0.0.0.dist-info/METADATA
fuchur-0.0.0.dist-info/WHEEL
fuchur-0.0.0.dist-info/entry_points.txt
fuchur-0.0.0.dist-info/top_level.txt
fuchur-0.0.0.dist-info/RECORD
